Metadata-Version: 1.1
Name: dev-identify
Version: 0.0.1
Summary: A simple python wrapper for dev-identify image grabber.
Home-page: https://github.com/rahulhaque/dev-identify-python
Author: Rahul Haque
Author-email: rahulhaque07@gmail.com
License: MIT
Download-URL: https://github.com/rahulhaque/dev-identify-python/archive/v0.0.1.tar.gz
Keywords: python,dev-identify,api-wrapper
Platform: UNKNOWN
Classifier: Development Status :: 3 - Alpha
Classifier: Intended Audience :: Developers
Classifier: License :: OSI Approved :: MIT License
Classifier: Programming Language :: Python :: 2
Classifier: Programming Language :: Python :: 3
